{
    "nom": "Configuration TradingView IA",
    "dateCapture": "2026-05-03T01:34:33.939Z",
    "serveur": {
        "apiAnalyse": "https://trading-pattern-api.onrender.com/api/analyse",
        "apiTest": "https://trading-pattern-api.onrender.com/api/test",
        "hebergeur": "Render",
        "type": "Node.js"
    },
    "graphique": {
        "actif": "BINANCE:BTCUSDT",
        "actifLibelle": "Bitcoin / USDT",
        "intervalle": "1",
        "intervalleLibelle": "1 minute",
        "indicateur": "RSI",
        "indicateurLibelle": "RSI",
        "typeBougie": "bougies_japonaises",
        "typeBougieLibelle": "Bougies japonaises",
        "source": "widget_tradingview_integre"
    },
    "analyseIA": {
        "categorie": "liquidite_marche",
        "categorieLibelle": "Liquidité de marché",
        "descriptionCategorie": "Liquidité de marché : volumes, carnets d’ordres, spreads et profondeur de marché.",
        "strategie": "suivi_tendance",
        "statut": "pret_pour_analyse"
    },
    "risque": {
        "capitalInitial": 1000,
        "risqueParPositionPourcent": 1,
        "stopLossPourcent": 2,
        "takeProfitPourcent": 4,
        "levier": 1,
        "sens": "achat_vente"
    },
    "snapshot": {
        "url": "",
        "categorieAnalyse": "liquidite_marche",
        "categorieAnalyseLibelle": "Liquidité de marché",
        "descriptionCategorieAnalyse": "Liquidité de marché : volumes, carnets d’ordres, spreads et profondeur de marché."
    },
    "notes": "",
    "limites": {
        "captureCompleteTradingView": false,
        "dessinsInternesTradingView": false,
        "remarque": "La page capture les paramètres contrôlés par l’interface HTML, la catégorie d’analyse et le lien éventuel du snapshot."
    }
}